CHANGES
LICENSE
MANIFEST.in
README.md
setup.py
pyzcasp/__init__.py
pyzcasp.egg-info/PKG-INFO
pyzcasp.egg-info/SOURCES.txt
pyzcasp.egg-info/dependency_links.txt
pyzcasp.egg-info/entry_points.txt
pyzcasp.egg-info/not-zip-safe
pyzcasp.egg-info/requires.txt
pyzcasp.egg-info/top_level.txt
pyzcasp/asp/__init__.py
pyzcasp/asp/adapters.py
pyzcasp/asp/impl.py
pyzcasp/asp/interfaces.py
pyzcasp/asp/utilities.py
pyzcasp/asp/tests/__init__.py
pyzcasp/asp/tests/groundersolver_fixt.py
pyzcasp/examples/__init__.py
pyzcasp/examples/files.py
pyzcasp/examples/simple.py
pyzcasp/examples/encodings/encoding-1-gringo3.lp
pyzcasp/examples/encodings/encoding-1-gringo4.lp
pyzcasp/examples/encodings/flies.lp
pyzcasp/examples/tweety/__init__.py
pyzcasp/examples/tweety/adapters.py
pyzcasp/examples/tweety/impl.py
pyzcasp/examples/tweety/interfaces.py
pyzcasp/examples/tweety/main.py
pyzcasp/potassco/__init__.py
pyzcasp/potassco/adapters.py
pyzcasp/potassco/impl.py
pyzcasp/potassco/interfaces.py
pyzcasp/potassco/utilities.py
pyzcasp/potassco/encodings/meta.lp
pyzcasp/potassco/encodings/metaD.lp
pyzcasp/potassco/encodings/metaO.lp
pyzcasp/potassco/tests/__init__.py
pyzcasp/potassco/tests/clasp2_fixt.py
pyzcasp/potassco/tests/clasp3_fixt.py
pyzcasp/potassco/tests/metagroundersolver_fixt.py