Metadata-Version: 1.0
Name: pyzcasp
Version: 1.0.1
Summary: Python + Zope Component Architecture framework for Answer Set Programming
Home-page: http://github.com/svidela/pyzcasp
Author: Santiago Videla
Author-email: santiago.videla@gmail.com
License: GPLv3+
Platform: UNKNOWN
Classifier: Intended Audience :: Science/Research
Classifier: License :: OSI Approved :: GNU General Public License v3 or later (GPLv3+)
Classifier: Operating System :: OS Independent
Classifier: Programming Language :: Python :: 2.7
Classifier: Topic :: Scientific/Engineering :: Artificial Intelligence
